ocpp/__init__.py
ocpp/charge_point.py
ocpp/exceptions.py
ocpp/messages.py
ocpp/routing.py
ocpp/v16/__init__.py
ocpp/v16/call.py
ocpp/v16/call_result.py
ocpp/v16/datatypes.py
ocpp/v16/enums.py
ocpp/v16/schemas/Authorize.json
ocpp/v16/schemas/AuthorizeResponse.json
ocpp/v16/schemas/BootNotification.json
ocpp/v16/schemas/BootNotificationResponse.json
ocpp/v16/schemas/CancelReservation.json
ocpp/v16/schemas/CancelReservationResponse.json
ocpp/v16/schemas/CertificateSigned.json
ocpp/v16/schemas/CertificateSignedResponse.json
ocpp/v16/schemas/ChangeAvailability.json
ocpp/v16/schemas/ChangeAvailabilityResponse.json
ocpp/v16/schemas/ChangeConfiguration.json
ocpp/v16/schemas/ChangeConfigurationResponse.json
ocpp/v16/schemas/ClearCache.json
ocpp/v16/schemas/ClearCacheResponse.json
ocpp/v16/schemas/ClearChargingProfile.json
ocpp/v16/schemas/ClearChargingProfileResponse.json
ocpp/v16/schemas/DataTransfer.json
ocpp/v16/schemas/DataTransferResponse.json
ocpp/v16/schemas/DeleteCertificate.json
ocpp/v16/schemas/DeleteCertificateResponse.json
ocpp/v16/schemas/DiagnosticsStatusNotification.json
ocpp/v16/schemas/DiagnosticsStatusNotificationResponse.json
ocpp/v16/schemas/ExtendedTriggerMessage.json
ocpp/v16/schemas/ExtendedTriggerMessageResponse.json
ocpp/v16/schemas/FirmwareStatusNotification.json
ocpp/v16/schemas/FirmwareStatusNotificationResponse.json
ocpp/v16/schemas/GetCompositeSchedule.json
ocpp/v16/schemas/GetCompositeScheduleResponse.json
ocpp/v16/schemas/GetConfiguration.json
ocpp/v16/schemas/GetConfigurationResponse.json
ocpp/v16/schemas/GetDiagnostics.json
ocpp/v16/schemas/GetDiagnosticsResponse.json
ocpp/v16/schemas/GetInstalledCertificateIds.json
ocpp/v16/schemas/GetInstalledCertificateIdsResponse.json
ocpp/v16/schemas/GetLocalListVersion.json
ocpp/v16/schemas/GetLocalListVersionResponse.json
ocpp/v16/schemas/GetLog.json
ocpp/v16/schemas/GetLogResponse.json
ocpp/v16/schemas/Heartbeat.json
ocpp/v16/schemas/HeartbeatResponse.json
ocpp/v16/schemas/InstallCertificate.json
ocpp_van-0.26.0.dist-info/LICENSE
ocpp_van-0.26.0.dist-info/METADATA
ocpp_van-0.26.0.dist-info/WHEEL
ocpp_van-0.26.0.dist-info/RECORD
