Metadata-Version: 2.1
Name: ocpp-van
Version: 0.26.0
Summary: VANSON FORK: Python package implementing the JSON version of the Open Charge Point Protocol (OCPP).
Home-page: https://github.com/VansonLeung/ocpp-van
License: MIT
Author: André Duarte
Author-email: andre15x@gmail.com
Requires-Python: >=3.7,<4.0
Classifier: Development Status :: 5 - Production/Stable
Classifier: License :: OSI Approved :: MIT License
Classifier: Programming Language :: Python :: 3
Classifier: Programming Language :: Python :: 3.7
Classifier: Programming Language :: Python :: 3.8
Classifier: Programming Language :: Python :: 3.9
Classifier: Programming Language :: Python :: 3.10
Classifier: Programming Language :: Python :: 3.11
Classifier: Programming Language :: Python :: 3.12
Requires-Dist: jsonschema (>=4.4.0,<5.0.0)
Project-URL: Documentation, https://ocpp.readthedocs.io/en/latest/
Project-URL: Repository, https://github.com/VansonLeung/ocpp-van
